glao_psf/.DS_Store
glao_psf/__init__.py
glao_psf/_version.py
glao_psf/dimg.py
glao_psf/example.cfg
glao_psf/flog.py
glao_psf/img.py
glao_psf/infoArray.py
glao_psf/keck.cfg
glao_psf/oprint.py
glao_psf/psf.py
glao_psf/psf_fe.py
glao_psf/readfits.py
glao_psf/test.py
glao_psf/tmt.cfg
glao_psf/units.py
glao_psf/data/Cn2_profiles.hd5
glao_psf/data/cn2.csv
glao_psf-0.3.1.dist-info/DESCRIPTION.rst
glao_psf-0.3.1.dist-info/METADATA
glao_psf-0.3.1.dist-info/RECORD
glao_psf-0.3.1.dist-info/WHEEL
glao_psf-0.3.1.dist-info/metadata.json
glao_psf-0.3.1.dist-info/top_level.txt
