Metadata-Version: 2.0
Name: glao-psf
Version: 0.3.1
Summary: Adaptive Optics Structure Function and Average PSF calculator
Home-page: https://bitbucket.org/donald_gavel/glao_psf
Author: Don Gavel
Author-email: donald.gavel@gmail.com
License: UNKNOWN
Download-URL: https://bitbucket.org/donald_gavel/glao_psf/downloads
Keywords: Adaptive Optics
Platform: UNKNOWN
Requires-Dist: h5py
Requires-Dist: matplotlib
Requires-Dist: numpy
Requires-Dist: pandas
Requires-Dist: pyfits
Requires-Dist: scipy
Requires-Dist: six
Requires-Dist: tables
